Metadata-Version: 2.1
Name: trollflow
Version: 0.6.0
Summary: Pytroll workflow execution framework
Home-page: https://github.com/pytroll/trollflow
Author: Martin Raspaud
Author-email: martin.raspaud@smhi.se
License: UNKNOWN
Platform: UNKNOWN
Classifier: Development Status :: 3 - Alpha
Classifier: Intended Audience :: Science/Research
Classifier: License :: OSI Approved :: GNU General Public License v3 or later (GPLv3+)
Classifier: Operating System :: OS Independent
Classifier: Programming Language :: Python
Classifier: Topic :: Scientific/Engineering
Requires-Dist: pyyaml
